AUTHORS.rst
CONTRIBUTING.rst
HISTORY.rst
LICENSE
MANIFEST.in
README.rst
setup.cfg
setup.py
django_remote_scenario.egg-info/PKG-INFO
django_remote_scenario.egg-info/SOURCES.txt
django_remote_scenario.egg-info/dependency_links.txt
django_remote_scenario.egg-info/not-zip-safe
django_remote_scenario.egg-info/top_level.txt
django_rs/__init__.py
django_rs/urls.py
django_rs/views.py
django_rs/.ropeproject/config.py
django_rs/management/__init__.py
django_rs/management/commands/__init__.py
django_rs/management/commands/rune2eserver.py
django_rs/management/commands/runserver_patched.py
django_rs/management/commands/.ropeproject/config.py
django_rs/static/css/bootstrap.min.css
django_rs/static/css/styles.css
django_rs/static/fonts/glyphicons-halflings-regular.svg
django_rs/static/js/bootstrap.min.js
django_rs/static/js/npm.js
django_rs/static/js/script.js
django_rs/templates/index.html