Metadata-Version: 1.1
Name: django-remote-scenario
Version: 0.3.1
Summary: Remote scenario setup for e2e testing of django projects
Home-page: https://github.com/skalanux/django-remote-scenario
Author: Juan Manuel Schillaci
Author-email: jmschillaci@gmail.com
License: GPLv3+
Keywords: django-remote-scenario
Platform: UNKNOWN
Classifier: Development Status :: 3 - Alpha
Classifier: Framework :: Django
Classifier: Intended Audience :: Developers
Classifier: License :: OSI Approved :: GNU General Public License v3 or later (GPLv3+)
Classifier: Natural Language :: English
Classifier: Programming Language :: Python :: 2
Classifier: Programming Language :: Python :: 2.6
Classifier: Programming Language :: Python :: 2.7
Classifier: Programming Language :: Python :: 3
Classifier: Programming Language :: Python :: 3.3
